MANIFEST.in
README.rst
bootstrap.py
buildout.cfg
setup.cfg
setup.py
isv_scores/scores-dev_R
isv_scores/scores-eval_M
isv_scores/scores-eval_R
maskattack/__init__.py
maskattack.lbp.egg-info/PKG-INFO
maskattack.lbp.egg-info/SOURCES.txt
maskattack.lbp.egg-info/dependency_links.txt
maskattack.lbp.egg-info/entry_points.txt
maskattack.lbp.egg-info/namespace_packages.txt
maskattack.lbp.egg-info/requires.txt
maskattack.lbp.egg-info/top_level.txt
maskattack.lbp.egg-info/zip-safe
maskattack/lbp/__init__.py
maskattack/lbp/ml/__init__.py
maskattack/lbp/ml/lda.py
maskattack/lbp/ml/norm.py
maskattack/lbp/ml/pca.py
maskattack/lbp/script/__init__.py
maskattack/lbp/script/barplot.py
maskattack/lbp/script/calclbp.py
maskattack/lbp/script/cmphistmodels.py
maskattack/lbp/script/ldatrain_lbp.py
maskattack/lbp/script/svmtrain_lbp.py
maskattack/lbp/spoof/__init__.py
maskattack/lbp/spoof/calclbp.py
maskattack/lbp/spoof/chi2.py