Metadata-Version: 1.0
Name: maskattack.lbp
Version: 1.0.4
Summary: Texture (LBP) based counter-measures for the 3D MASK ATTACK database
Home-page: http://github.com/bioidiap/maskattack.lbp
Author: Nesli Erdogmus
Author-email: nesli.erdogmus@idiap.ch
License: GPLv3
Platform: UNKNOWN
